quenv/__init__.py
quenv/ai/__init__.py
quenv/ai/steps/__init__.py
quenv/ai/steps/ai_greedy.py
quenv/ai/steps/ai_log.py
quenv/ai/steps/ai_phys.py
quenv/ai/steps/ai_random.py
quenv/ai/steps/ai_rl.py
quenv/ai/steps/env_model.py
quenv/ai/steps/memory_buf.py
quenv/ai/steps/utils.py
quenv/environment/__init__.py
quenv/environment/pygame/__init__.py
quenv/environment/pygame/car.py
quenv/environment/pygame/environment.py
QuEnv-0.0.7.dist-info/METADATA
QuEnv-0.0.7.dist-info/WHEEL
QuEnv-0.0.7.dist-info/top_level.txt
QuEnv-0.0.7.dist-info/RECORD
