Metadata-Version: 2.1
Name: QuEnv
Version: 0.0.7
Summary: Working with multi-agent vehicle environments
Home-page: https://github.com/step137/car_agents
Author: synset
Author-email: steps137ai@gmail.com
License: UNKNOWN
Platform: UNKNOWN
Classifier: Programming Language :: Python :: 3
Classifier: License :: OSI Approved :: MIT License
Classifier: Operating System :: OS Independent
